clotho.py
Clotho-0.1.0.dist-info/LICENSE
Clotho-0.1.0.dist-info/METADATA
Clotho-0.1.0.dist-info/WHEEL
Clotho-0.1.0.dist-info/entry_points.txt
Clotho-0.1.0.dist-info/top_level.txt
Clotho-0.1.0.dist-info/RECORD
