Metadata-Version: 2.1
Name: Clotho
Version: 0.1.0
Summary: Proxy requests to AWS public endpoints and filter them using an allowlist
Home-page: https://github.com/ClothoProxy/PyClotho
Author: CostasK
License: MIT
Keywords: aws proxy cross-account security
Classifier: Programming Language :: Python :: 3.9
Classifier: License :: OSI Approved :: MIT License
Classifier: Operating System :: OS Independent
Requires-Python: >=3.9
License-File: LICENSE
Requires-Dist: mitmproxy ==10.2.2
Requires-Dist: PyYAML ==6.0.1
